greyhorse/__init__.py
greyhorse/enum.py
greyhorse/error.py
greyhorse/factory.py
greyhorse/logging.py
greyhorse/maybe.py
greyhorse/mypy_plugin.py
greyhorse/py.typed
greyhorse/result.py
greyhorse/run.py
greyhorse/translations.toml
greyhorse/app/__init__.py
greyhorse/app/contexts.py
greyhorse/app/messagebus.py
greyhorse/app/abc/__init__.py
greyhorse/app/abc/component.py
greyhorse/app/abc/module.py
greyhorse/app/abc/providers.py
greyhorse/app/abc/collections/__init__.py
greyhorse/app/abc/collections/collectors.py
greyhorse/app/abc/collections/registries.py
greyhorse/app/abc/collections/selectors.py
greyhorse/app/abc/functional/__init__.py
greyhorse/app/abc/functional/context.py
greyhorse/app/abc/functional/operators.py
greyhorse/app/abc/functional/registries.py
greyhorse/app/abc/functional/resolver.py
greyhorse/app/abc/resources/__init__.py
greyhorse/app/abc/resources/borrow.py
greyhorse/app/abc/resources/common.py
greyhorse/app/abc/resources/operators.py
greyhorse/app/abc/resources/providers.py
greyhorse/app/abc/resources/reconciler.py
greyhorse/app/abc/resources/state.py
greyhorse/app/abc/runtime/__init__.py
greyhorse/app/abc/runtime/runtime.py
greyhorse/app/entities/__init__.py
greyhorse/app/entities/application.py
greyhorse/app/entities/boxes.py
greyhorse/app/private/__init__.py
greyhorse/app/private/component.py
greyhorse/app/private/controllers.py
greyhorse/app/private/fragment.py
greyhorse/app/private/module.py
greyhorse/app/private/services.py
greyhorse/app/private/builders/__init__.py
greyhorse/app/private/builders/loader.py
greyhorse/app/private/builders/module.py
greyhorse/app/private/collections/__init__.py
greyhorse/app/private/collections/registries.py
greyhorse/app/private/functional/__init__.py
greyhorse/app/private/functional/bucket.py
greyhorse/app/private/functional/context.py
greyhorse/app/private/functional/factory_storage.py
greyhorse/app/private/functional/operators.py
greyhorse/app/private/functional/resolver.py
greyhorse-0.5.0.dist-info/METADATA
greyhorse-0.5.0.dist-info/WHEEL
greyhorse-0.5.0.dist-info/RECORD
